README.rst
setup.py
buildbot_washer.egg-info/PKG-INFO
buildbot_washer.egg-info/SOURCES.txt
buildbot_washer.egg-info/dependency_links.txt
buildbot_washer.egg-info/entry_points.txt
buildbot_washer.egg-info/requires.txt
buildbot_washer.egg-info/top_level.txt
washer/__init__.py
washer/master/__init__.py
washer/master/recursiverender.py
washer/master/remotecommand.py
washer/master/steps/__init__.py
washer/master/steps/reducetriggerproperties.py
washer/master/steps/triggerfromfile.py
washer/master/steps/washertask.py
washer/master/worker/__init__.py
washer/master/worker/docker.py
washer/worker/__init__.py
washer/worker/__main__.py
washer/worker/actions.py
washer/worker/commands.py
washer/worker/conf.py
washer/worker/worker.py