Metadata-Version: 1.1
Name: buildbot-washer
Version: 1.2.0
Summary: Buildbot Utility Library
Home-page: UNKNOWN
Author: Roberto Abdelkader Martínez Pérez
Author-email: robertomartinezp@gmail.com
License: Apache
Platform: UNKNOWN
Classifier: Development Status :: 4 - Beta
Classifier: Intended Audience :: Developers
Classifier: Framework :: Buildout :: Extension
Classifier: License :: OSI Approved :: Apache Software License
Classifier: Programming Language :: Python
Classifier: Programming Language :: Python :: 3.4
Classifier: Programming Language :: Python :: 3.5
Classifier: Programming Language :: Python :: 3.6
Classifier: Topic :: Software Development :: Testing
